CHANGES.txt
LICENSE.txt
MANIFEST.in
README.txt
bootstrap.py
buildout.cfg
mongodb.cfg
setup.py
testing.cfg
versions.cfg
ztk-versions-1.1.2.cfg
parts/test-pkgs/s01.demo/0.16.2/2.7/CHANGES.txt
parts/test-pkgs/s01.demo/0.16.2/2.7/LICENSE.txt
parts/test-pkgs/s01.demo/0.16.2/2.7/README.txt
parts/test-pkgs/s01.demo/0.16.2/2.7/src/s01.demo.egg-info/SOURCES.txt
parts/test-pkgs/s01.demo/0.16.2/2.7/src/s01.demo.egg-info/dependency_links.txt
parts/test-pkgs/s01.demo/0.16.2/2.7/src/s01.demo.egg-info/namespace_packages.txt
parts/test-pkgs/s01.demo/0.16.2/2.7/src/s01.demo.egg-info/requires.txt
parts/test-pkgs/s01.demo/0.16.2/2.7/src/s01.demo.egg-info/top_level.txt
src/s01/__init__.py
src/s01.worker.egg-info/PKG-INFO
src/s01.worker.egg-info/SOURCES.txt
src/s01.worker.egg-info/dependency_links.txt
src/s01.worker.egg-info/entry_points.txt
src/s01.worker.egg-info/namespace_packages.txt
src/s01.worker.egg-info/not-zip-safe
src/s01.worker.egg-info/requires.txt
src/s01.worker.egg-info/top_level.txt
src/s01/worker/README.txt
src/s01/worker/__init__.py
src/s01/worker/app.zcml
src/s01/worker/configure.zcml
src/s01/worker/error.py
src/s01/worker/error.zcml
src/s01/worker/interfaces.py
src/s01/worker/jsonrpc.py
src/s01/worker/jsonrpc.zcml
src/s01/worker/layer.py
src/s01/worker/layer.zcml
src/s01/worker/package.py
src/s01/worker/package.zcml
src/s01/worker/publish.py
src/s01/worker/publisher.py
src/s01/worker/publisher.zcml
src/s01/worker/pypi.py
src/s01/worker/root.py
src/s01/worker/root.zcml
src/s01/worker/security.zcml
src/s01/worker/tests.py
src/s01/worker/traverser.py
src/s01/worker/traverser.zcml
src/s01/worker/util.py
src/s01/worker/wsgi.py
src/s01/worker/schema/productconfig.xml
src/s01/worker/schema/schema.xml
src/s01/worker/testing/__init__.py
src/s01/worker/testing/debug.py
src/s01/worker/testing/ftesting.zcml
src/s01/worker/testing/mongodb/README.txt
src/s01/worker/testing/pypi/s01.demo-0.16.2.zip